bayesreconpy/PMF.py
bayesreconpy/__init__.py
bayesreconpy/hierarchy.py
bayesreconpy/reconc_buis.py
bayesreconpy/reconc_gaussian.py
bayesreconpy/reconc_mcmc.py
bayesreconpy/reconc_mint.py
bayesreconpy/reconc_mix_cond.py
bayesreconpy/reconc_ols.py
bayesreconpy/reconc_td_cond.py
bayesreconpy/shrink_cov.py
bayesreconpy/utils.py
bayesreconpy-0.3.3.dist-info/licenses/LICENSE.md
data/M5_CA1_check.py
data/Probabilistic Reconciliation via Conditioning.py
data/reconciliation_properties_check.py
docs/conf.py
tests/__init__.py
tests/test_recon.py
tests/test_utils.py
bayesreconpy-0.3.3.dist-info/METADATA
bayesreconpy-0.3.3.dist-info/WHEEL
bayesreconpy-0.3.3.dist-info/top_level.txt
bayesreconpy-0.3.3.dist-info/RECORD
