Metadata-Version: 2.4
Name: bayesreconpy
Version: 0.3.3
Summary: Bayesian reconciliation for hierarchical forecasting
Author: A.Biswas
Author-email: "L.Nespoli" <anubhab.biswas@supsi.ch>
License: MIT
Project-URL: Homepage, https://github.com/supsi-dacd-isaac/BayesReconPy
Keywords: forecasting,reconciliation,bayesian,hierarchical
Classifier: Programming Language :: Python :: 3
Classifier: License :: OSI Approved :: MIT License
Classifier: Operating System :: OS Independent
Requires-Python: >=3.10
License-File: LICENSE.md
Requires-Dist: numpy>=2.0.2
Requires-Dist: pandas>=2.2.2
Requires-Dist: PuLP>=2.9.0
Requires-Dist: scipy>=1.14.1
Requires-Dist: KDEpy>=1.1.10
Dynamic: license-file
